[
  {
    "by" : "pmoriarty",
    "descendants" : 22,
    "id" : 17052185,
    "kids" : [ 17053523, 17053370, 17053514, 17053574, 17053760, 17053788 ],
    "score" : 137,
    "time" : 1526092265,
    "title" : "Man donated blood every week for 60 years and helped save 2.4M babies",
    "type" : "story",
    "url" : "https://www.independent.co.uk/news/world/australasia/james-harrison-man-golden-arm-blood-donor-60-years-millions-babies-a8347896.html"
  },
  {
    "by" : "nreece",
    "descendants" : 0,
    "id" : 17052182,
    "score" : 2,
    "time" : 1526092166,
    "title" : "How does Stack Overflow do pagination",
    "type" : "story",
    "url" : "https://meta.stackoverflow.com/questions/322164/how-does-stack-overflow-do-pagination/322246#322246"
  },
  {
    "by" : "beefman",
    "descendants" : 0,
    "id" : 17051512,
    "score" : 7,
    "time" : 1526082174,
    "title" : "Fieldbook is shutting down",
    "type" : "story",
    "url" : "https://medium.com/the-fieldbook-blog/fieldbook-is-shutting-down-db4d2b3eec2d"
  },
  {
    "by" : "imartin2k",
    "descendants" : 114,
    "id" : 17051508,
    "kids" : [ 17052026, 17052623, 17052633, 17052426, 17054209, 17052618, 17052861, 17052195, 17052878, 17052434, 17052941, 17052223, 17051697, 17053013, 17051891, 17052131, 17053689, 17053002, 17052796, 17052995, 17052197, 17052675, 17052071, 17051848 ],
    "score" : 207,
    "time" : 1526082108,
    "title" : "On Cumulative Advantage and How to Think About Luck",
    "type" : "story",
    "url" : "https://ofdollarsanddata.com/why-winners-keep-winning-4e7f221f5b84"
  },
  {
    "by" : "camtarn",
    "descendants" : 0,
    "id" : 17051495,
    "score" : 1,
    "time" : 1526081970,
    "title" : "Police have ruined my life, says woman living in witness protection",
    "type" : "story",
    "url" : "https://www.theguardian.com/law/2018/may/11/police-ruined-life-says-woman-living-witness-protection"
  }
]
